aiosendpulse/__init__.py
aiosendpulse/auth.py
aiosendpulse/client.py
aiosendpulse/exceptions.py
aiosendpulse/logger.py
aiosendpulse/methods/__init__.py
aiosendpulse/methods/authorize.py
aiosendpulse/methods/base.py
aiosendpulse/methods/email/__init__.py
aiosendpulse/methods/email/addressbook/__init__.py
aiosendpulse/methods/email/addressbook/add_emails_to_addressbook.py
aiosendpulse/methods/email/addressbook/create_addressbook.py
aiosendpulse/methods/email/addressbook/edit_addressbook.py
aiosendpulse/methods/email/addressbook/get_addressbook.py
aiosendpulse/methods/email/addressbook/get_emails_from_addressbook.py
aiosendpulse/methods/email/addressbook/get_list_of_addressbook.py
aiosendpulse/methods/email/addressbook/get_list_of_addressbook_variables.py
aiosendpulse/methods/email/addressbook/get_total_emails.py
aiosendpulse/methods/email/addressbook/search_emails.py
aiosendpulse/methods/email/blacklist/__init__.py
aiosendpulse/methods/email/blacklist/add_emails_to_blacklist.py
aiosendpulse/methods/email/blacklist/delete_emails_from_blacklist.py
aiosendpulse/methods/email/templates/__init__.py
aiosendpulse/methods/email/templates/create_template.py
aiosendpulse/methods/email/templates/edit_template.py
aiosendpulse/methods/email/templates/get_template.py
aiosendpulse/methods/smtp/__init__.py
aiosendpulse/methods/smtp/send_email.py
aiosendpulse/services/__init__.py
aiosendpulse/services/base.py
aiosendpulse/services/email/__init__.py
aiosendpulse/services/email/addressbook.py
aiosendpulse/services/email/blacklist.py
aiosendpulse/services/email/email.py
aiosendpulse/services/email/template.py
aiosendpulse/services/smtp/__init__.py
aiosendpulse/services/smtp/smtp.py
aiosendpulse/storage/__init__.py
aiosendpulse/storage/base.py
aiosendpulse/storage/exceptions.py
aiosendpulse/storage/redis.py
aiosendpulse/types/__init__.py
aiosendpulse/types/addressbook.py
aiosendpulse/types/addressbook_variable.py
aiosendpulse/types/base.py
aiosendpulse/types/email.py
aiosendpulse-0.0.6.dist-info/METADATA
aiosendpulse-0.0.6.dist-info/WHEEL
aiosendpulse-0.0.6.dist-info/RECORD
